{"assets":{"09B5FC69CD826C75EBFCF538C72EE8DE":{"type":"texture","index":85,"assetRequest":{"type":"slide","state":"incoming","slide":"9E6DFD31-4D35-46EF-AEB3-5C7C66C75BC7"},"url":"assets/09B5FC69CD826C75EBFCF538C72EE8DE.svg","width":1024,"height":768},"12146E9D7235D6745A2620B96747B816":{"type":"texture","index":84,"assetRequest":{"type":"slide","state":"outgoing","slide":"B55545B8-648A-474C-A83D-F6956EE6A70C"},"url":"assets/12146E9D7235D6745A2620B96747B816.svg","width":1024,"height":768}},"events":[{"effects":[{"beginTime":0,"baseLayer":{"animations":[],"initialState":{"affineTransform":[1,0,0,1,0,0],"masksToBounds":true,"rotation":0,"scale":1,"position":{"pointX":512,"pointY":384},"width":1024,"sublayerTransform":[1,0,0,0,0,1,0,0,0,0,1,0,0,0,0,1],"contentsRect":{"y":0,"x":0,"width":1,"height":1},"opacity":1,"edgeAntialiasingMask":0,"height":768,"hidden":false,"anchorPoint":{"pointX":0.5,"pointY":0.5}},"objectID":"0","layers":[{"animations":[],"initialState":{"affineTransform":[1,0,0,1,0,0],"masksToBounds":false,"rotation":0,"scale":1,"position":{"pointX":512,"pointY":384},"width":1024,"sublayerTransform":[1,0,0,0,0,1,0,0,0,0,1,-0.0004922987690640373,0,0,0,1],"contentsRect":{"y":0,"x":0,"width":1,"height":1},"opacity":1,"edgeAntialiasingMask":15,"height":768,"hidden":false,"anchorPoint":{"pointX":0.5,"pointY":0.5}},"layers":[{"animations":[],"layers":[],"initialState":{"affineTransform":[1,0,0,1,0,0],"masksToBounds":false,"rotation":0,"scale":1,"position":{"pointX":512,"pointY":384},"width":1024,"sublayerTransform":[1,0,0,0,0,1,0,0,0,0,1,0,0,0,0,1],"contentsRect":{"y":0,"x":0,"width":1,"height":1},"opacity":1,"edgeAntialiasingMask":0,"height":768,"hidden":false,"anchorPoint":{"pointX":0.5,"pointY":0.5}},"texture":"09B5FC69CD826C75EBFCF538C72EE8DE"},{"animations":[{"from":{"scalar":false},"beginTime":0,"repeatCount":0,"fillMode":"both","property":"hidden","duration":0.01,"to":{"scalar":true}}],"layers":[],"initialState":{"affineTransform":[1,0,0,1,0,0],"masksToBounds":false,"rotation":0,"scale":1,"position":{"pointX":512,"pointY":384},"width":1024,"sublayerTransform":[1,0,0,0,0,1,0,0,0,0,1,0,0,0,0,1],"contentsRect":{"y":0,"x":0,"width":1,"height":1},"opacity":1,"edgeAntialiasingMask":0,"height":768,"hidden":false,"anchorPoint":{"pointX":0.5,"pointY":0.5}},"texture":"12146E9D7235D6745A2620B96747B816"}]}]},"effects":[],"duration":0.01,"type":"transition","name":"none","objectID":"0"}],"automaticPlay":false,"hyperlinks":[{"url":"http://j.mp/psumac13","targetRectangle":{"y":735.0888670086861,"x":446.56884765625,"width":244.0625,"height":26}}],"accessibility":[{"text":"$ ls -l /dev","targetRectangle":{"y":203.5,"x":57.1767578125,"width":180.029296875,"height":30.91259765625}},{"text":"total 0","targetRectangle":{"y":236.5,"x":57.1767578125,"width":105.01708984375,"height":30.91259765625}},{"text":"crw------- 1 root    wheel    14,  1 Jun 21 21:11 afsc_type5","targetRectangle":{"y":269.5,"x":57.1767578125,"width":900.146484375,"height":30.91259765625}},{"text":"crw------- 1 root    wheel     8,  1 Jun 21 21:11 auditpipe","targetRectangle":{"y":302.5,"x":57.1767578125,"width":885.14404296875,"height":30.91259765625}},{"text":"…","targetRectangle":{"y":335.5,"x":57.1767578125,"width":15.00244140625,"height":30.91259765625}},{"text":"brw------- 1 root    operator  2,  3 Jun 21 21:11 vn3","targetRectangle":{"y":368.5,"x":57.1767578125,"width":795.12939453125,"height":30.91259765625}},{"text":"crw-rw-rw- 1 root    wheel     3,  3 Jun 21 21:11 zero","targetRectangle":{"y":401.5,"x":57.1767578125,"width":810.1318359375,"height":30.91259765625}},{"text":"Screen Shot 2013-05-01 at 11.54.35 AM.png","targetRectangle":{"y":102,"x":30,"width":963,"height":564}},{"text":"Feedback: http://j.mp/psumac13","targetRectangle":{"y":735.0888670086861,"x":332.36865234375,"width":358.2626953125,"height":26}}],"baseLayer":{"animations":[],"initialState":{"affineTransform":[1,0,0,1,0,0],"masksToBounds":true,"rotation":0,"scale":1,"position":{"pointX":512,"pointY":384},"width":1024,"sublayerTransform":[1,0,0,0,0,1,0,0,0,0,1,0,0,0,0,1],"contentsRect":{"y":0,"x":0,"width":1,"height":1},"opacity":1,"edgeAntialiasingMask":0,"height":768,"hidden":false,"anchorPoint":{"pointX":0.5,"pointY":0.5}},"objectID":"0","layers":[{"animations":[],"initialState":{"affineTransform":[1,0,0,1,0,0],"masksToBounds":false,"rotation":0,"scale":1,"position":{"pointX":512,"pointY":384},"width":1024,"sublayerTransform":[1,0,0,0,0,1,0,0,0,0,1,-0.0004922987690640373,0,0,0,1],"contentsRect":{"y":0,"x":0,"width":1,"height":1},"opacity":1,"edgeAntialiasingMask":15,"height":768,"hidden":false,"anchorPoint":{"pointX":0.5,"pointY":0.5}},"layers":[{"animations":[],"layers":[],"initialState":{"affineTransform":[1,0,0,1,0,0],"masksToBounds":false,"rotation":0,"scale":1,"position":{"pointX":512,"pointY":384},"width":1024,"sublayerTransform":[1,0,0,0,0,1,0,0,0,0,1,0,0,0,0,1],"contentsRect":{"y":0,"x":0,"width":1,"height":1},"opacity":1,"edgeAntialiasingMask":0,"height":768,"hidden":false,"anchorPoint":{"pointX":0.5,"pointY":0.5}},"texture":"12146E9D7235D6745A2620B96747B816"}]}]}}]}